symbolic_pursuit/__init__.py
symbolic_pursuit/logger.py
symbolic_pursuit/models.py
symbolic_pursuit/version.py
symbolic_pursuit/pysymbolic/__init__.py
symbolic_pursuit/pysymbolic/models/__init__.py
symbolic_pursuit/pysymbolic/models/special_functions.py
symbolic_pursuit-0.0.2.dist-info/LICENSE
symbolic_pursuit-0.0.2.dist-info/METADATA
symbolic_pursuit-0.0.2.dist-info/WHEEL
symbolic_pursuit-0.0.2.dist-info/top_level.txt
symbolic_pursuit-0.0.2.dist-info/RECORD
