Metadata-Version: 2.1
Name: symbolic-pursuit
Version: 0.0.2
Summary: Learning outside the black-box: at the pursuit of interpretable models
Home-page: https://www.vanderschaar-lab.com/
Author: Jonathan Crabbé
Author-email: jc2133@cam.ac.uk
License: MIT
Project-URL: Documentation, https://pyscaffold.org/
Platform: any
Classifier: Programming Language :: Python :: 3
Classifier: Topic :: Scientific/Engineering :: Artificial Intelligence
Classifier: Intended Audience :: Science/Research
Classifier: License :: OSI Approved :: MIT License
Classifier: Operating System :: OS Independent
License-File: LICENSE
Requires-Dist: loguru
Requires-Dist: numpy
Requires-Dist: scikit-learn
Requires-Dist: sympy
Requires-Dist: importlib-metadata; python_version < "3.8"
Provides-Extra: testing
Requires-Dist: pre-commit; extra == "testing"
Requires-Dist: setuptools; extra == "testing"
Requires-Dist: pytest; extra == "testing"
Requires-Dist: pytest-cov; extra == "testing"
Requires-Dist: bandit; extra == "testing"
Requires-Dist: jupyter; extra == "testing"
Requires-Dist: notebook; extra == "testing"
Requires-Dist: black; extra == "testing"
Requires-Dist: catboost; extra == "testing"
Requires-Dist: cite2c==0.2.1; extra == "testing"
Requires-Dist: flake8; extra == "testing"
Requires-Dist: lime==0.2.0.1; extra == "testing"
Requires-Dist: sklearn; extra == "testing"
Requires-Dist: xgboost; extra == "testing"
